monipy/__init__.py
monipy/__version__.py
monipy/app.py
monipy/collectors.py
monipy/databases.py
monipy/main.py
monipy/templates/__init__.py
monipy/templates/index.html.jinja
monipy-0.1.0.dist-info/entry_points.txt
monipy-0.1.0.dist-info/WHEEL
monipy-0.1.0.dist-info/METADATA
monipy-0.1.0.dist-info/RECORD
