Metadata-Version: 2.1
Name: monipy
Version: 0.1.0
Summary: Web-dashboard for resource monitoring data.
Home-page: https://github.com/kpj/monipy
License: MIT
Author: kpj
Author-email: kim.philipp.jablonski@gmail.com
Requires-Python: >=3.8.0,<4.0.0
Classifier: License :: OSI Approved :: MIT License
Classifier: Programming Language :: Python :: 3
Classifier: Programming Language :: Python :: 3.8
Classifier: Programming Language :: Python :: 3.9
Requires-Dist: Jinja2 (>=2.11.3,<3.0.0)
Requires-Dist: fastapi (>=0.63.0,<0.64.0)
Requires-Dist: loguru (>=0.5.3,<0.6.0)
Requires-Dist: natsort (>=7.1.1,<8.0.0)
Requires-Dist: palettable (>=3.3.0,<4.0.0)
Requires-Dist: pandas (>=1.2.4,<2.0.0)
Requires-Dist: rrdtool (>=0.1.15,<0.2.0)
Requires-Dist: uvicorn (>=0.13.4,<0.14.0)
Project-URL: Repository, https://github.com/kpj/monipy
